LICENSE
version.py
cli/__init__.py
cli/cli.py
cli/config.py
cli/docker/deluge-compose.yml
cli/docker/gluetun-compose.yml
cli/docker/heimdall-compose.yml
cli/docker/jackett-compose.yml
cli/docker/plex-compose.yml
cli/docker/radarr-compose.yml
cli/docker/sonarr-compose.yml
linuxserver.egg-info/PKG-INFO
linuxserver.egg-info/SOURCES.txt
linuxserver.egg-info/dependency_links.txt
linuxserver.egg-info/entry_points.txt
linuxserver.egg-info/requires.txt
linuxserver.egg-info/top_level.txt
linuxserver-0.1.2.dist-info/LICENSE
linuxserver-0.1.2.dist-info/METADATA
linuxserver-0.1.2.dist-info/WHEEL
linuxserver-0.1.2.dist-info/entry_points.txt
linuxserver-0.1.2.dist-info/top_level.txt
linuxserver-0.1.2.dist-info/RECORD
