Metadata-Version: 2.1
Name: linuxserver
Version: 0.1.2
Summary: A simple CLI to deploy linuxserver services
Home-page: https://github.com/foprel/linuxserver
Author: Frank Oprel
Author-email: fj.oprel@gmail.com
License: Copyright (c) 2012-2022 Scott Chacon and others
Requires-Dist: Jinja2 (==3.1.2)
Requires-Dist: MarkupSafe (==2.1.1)
